HighGeoX/__init__.py
HighGeoX/module.py
HighGeoX-0.1.4.dist-info/LICENSE
HighGeoX-0.1.4.dist-info/METADATA
HighGeoX-0.1.4.dist-info/WHEEL
HighGeoX-0.1.4.dist-info/top_level.txt
HighGeoX-0.1.4.dist-info/RECORD
