Metadata-Version: 2.1
Name: HighGeoX
Version: 0.1.4
Summary: provides utilities to deal with large geospatial Datasets and provides functions for Fast computation of NDVI and MNDVI indces,
Home-page: UNKNOWN
Author: Deeksha Aggarwal
License: UNKNOWN
Platform: UNKNOWN
Classifier: Programming Language :: Python :: 3
Classifier: License :: OSI Approved :: MIT License
Classifier: Operating System :: OS Independent
License-File: LICENSE
Requires-Dist: dask
Requires-Dist: distributed
Requires-Dist: matplotlib
Requires-Dist: numpy
Requires-Dist: pandas
Requires-Dist: rasterio
Requires-Dist: scikit-learn
